teramesh_hardware_tester/__init__.py
teramesh_hardware_tester/__version__.py
teramesh_hardware_tester/configurer.py
teramesh_hardware_tester/dumper.py
teramesh_hardware_tester/efuser.py
teramesh_hardware_tester/modbus_server.py
teramesh_hardware_tester/modbuser.py
teramesh_hardware_tester/server.py
teramesh_hardware_tester/tester.py
teramesh_hardware_tester/idrc_esp_tools/__init__.py
teramesh_hardware_tester/idrc_esp_tools/analyze_nvs.py
teramesh_hardware_tester/idrc_esp_tools/at.py
teramesh_hardware_tester/idrc_esp_tools/gen_esp32part.py
teramesh_hardware_tester/idrc_esp_tools/nvs_partition_gen.py
teramesh_hardware_tester/idrc_esp_tools/serial_asyncio.py
teramesh_hardware_tester/idrc_esp_tools/sht85.py
teramesh_hardware_tester/idrc_esp_tools/smbus.py
teramesh_hardware_tester/tests/__init__.py
teramesh_hardware_tester/tests/test_main.py
teramesh_hardware_tester-0.9.0.dist-info/LICENSE
teramesh_hardware_tester-0.9.0.dist-info/METADATA
teramesh_hardware_tester-0.9.0.dist-info/WHEEL
teramesh_hardware_tester-0.9.0.dist-info/entry_points.txt
teramesh_hardware_tester-0.9.0.dist-info/top_level.txt
teramesh_hardware_tester-0.9.0.dist-info/RECORD
